swh/icinga_plugins/__init__.py
swh/icinga_plugins/base_check.py
swh/icinga_plugins/cli.py
swh/icinga_plugins/deposit.py
swh/icinga_plugins/py.typed
swh/icinga_plugins/save_code_now.py
swh/icinga_plugins/vault.py
swh/icinga_plugins/data/deposit/jesuisgpl.tgz
swh/icinga_plugins/data/deposit/jesuisgpl.tgz.xml
swh/icinga_plugins/tests/__init__.py
swh/icinga_plugins/tests/conftest.py
swh/icinga_plugins/tests/test_base_check.py
swh/icinga_plugins/tests/test_deposit.py
swh/icinga_plugins/tests/test_save_code_now.py
swh/icinga_plugins/tests/test_vault.py
swh/icinga_plugins/tests/utils.py
swh/icinga_plugins/tests/web_scenario.py
swh.icinga_plugins-0.7.1.dist-info/AUTHORS
swh.icinga_plugins-0.7.1.dist-info/LICENSE
swh.icinga_plugins-0.7.1.dist-info/METADATA
swh.icinga_plugins-0.7.1.dist-info/WHEEL
swh.icinga_plugins-0.7.1.dist-info/entry_points.txt
swh.icinga_plugins-0.7.1.dist-info/top_level.txt
swh.icinga_plugins-0.7.1.dist-info/RECORD
