Metadata-Version: 2.1
Name: swh.icinga_plugins
Version: 0.7.1
Summary: Icinga plugins for Software Heritage infrastructure monitoring
Author-email: Software Heritage developers <swh-devel@inria.fr>
Project-URL: Homepage, https://gitlab.softwareheritage.org/swh/devel/swh-icinga-plugins
Project-URL: Bug Reports, https://gitlab.softwareheritage.org/swh/devel/swh-icinga-plugins/-/issues
Project-URL: Funding, https://www.softwareheritage.org/donate
Project-URL: Documentation, https://docs.softwareheritage.org/devel/swh-icinga-plugins/
Project-URL: Source, https://gitlab.softwareheritage.org/swh/devel/swh-icinga-plugins.git
Classifier: Programming Language :: Python :: 3
Classifier: Intended Audience :: Developers
Classifier: License :: OSI Approved :: GNU General Public License v3 (GPLv3)
Classifier: Operating System :: OS Independent
Classifier: Development Status :: 3 - Alpha
Requires-Python: >=3.7
License-File: LICENSE
License-File: AUTHORS
Requires-Dist: click
Requires-Dist: psycopg2
Requires-Dist: requests
Requires-Dist: prometheus-client
Requires-Dist: swh.core[http] >=0.3
Requires-Dist: swh.deposit >=0.3
Requires-Dist: swh.storage >=0.0.162
Provides-Extra: testing
Requires-Dist: click ; extra == 'testing'
Requires-Dist: psycopg2 ; extra == 'testing'
Requires-Dist: requests ; extra == 'testing'
Requires-Dist: prometheus-client ; extra == 'testing'
Requires-Dist: swh.core[http] >=0.3 ; extra == 'testing'
Requires-Dist: swh.deposit >=0.3 ; extra == 'testing'
Requires-Dist: swh.storage >=0.0.162 ; extra == 'testing'
Requires-Dist: pytest >=8.1 ; extra == 'testing'
Requires-Dist: pytest-mock ; extra == 'testing'
Requires-Dist: requests-mock ; extra == 'testing'
Requires-Dist: types-click ; extra == 'testing'
Requires-Dist: types-requests ; extra == 'testing'
Requires-Dist: types-python-dateutil ; extra == 'testing'
Requires-Dist: types-PyYAML ; extra == 'testing'
